LICENSE
MANIFEST.in
README.rst
setup.py
HexOmega/__init__.py
HexOmega/settings.py
HexOmega/urls.py
HexOmega/wsgi.py
hexomega.egg-info/PKG-INFO
hexomega.egg-info/SOURCES.txt
hexomega.egg-info/dependency_links.txt
hexomega.egg-info/requires.txt
hexomega.egg-info/top_level.txt
log/Log.py
log/__init__.py
log/admin.py
log/apps.py
log/models.py
log/parse_to_html.py
log/tests.py
log/urls.py
log/views.py
log/migrations/__init__.py
log/templates/log/test.html
users/__init__.py
users/admin.py
users/apps.py
users/backends.py
users/filters.py
users/login_form.py
users/models.py
users/other.py
users/tasks.py
users/tests.py
users/urls.py
users/utils.py
users/views.py
users/Claudia/__init__.py
users/Claudia/add_user_form.py
users/Claudia/tests.py
users/Claudia/user_form.py
users/Claudia/views.py
users/Xav/__init__.py
users/Xav/add_leader_form.py
users/Xav/user_context.py
users/Xav/views.py
users/forms/__init__.py
users/forms/login_form.py
users/forms/member_form.py
users/forms/project_forms.py
users/forms/task_forms.py
users/management/__init__.py
users/management/commands/__init__.py
users/management/commands/run_scheduled.py
users/management/commands/setup_init.py
users/migrations/0001_initial.py
users/migrations/0002_auto_20170327_1709.py
users/migrations/0003_auto_20170405_1014.py
users/migrations/__init__.py
users/static/spc/jsi18n.js
users/static/users/css/Pe-icon-7-stroke.eot
users/static/users/css/Pe-icon-7-stroke.svg
users/static/users/css/Pe-icon-7-stroke.ttf
users/static/users/css/Pe-icon-7-stroke.woff
users/static/users/css/Roboto-Regular-webfont.eot
users/static/users/css/Roboto-Regular-webfont.svg
users/static/users/css/Roboto-Regular-webfont.ttf
users/static/users/css/Roboto-Regular-webfont.woff
users/static/users/css/animate.min.css
users/static/users/css/bootstrap.min.css
users/static/users/css/dashboard.css
users/static/users/css/full-slider.css
users/static/users/css/light-bootstrap-dashboard.css
users/static/users/css/pe-icon-7-stroke.css
users/static/users/css/style.css
users/static/users/fonts/glyphicons-halflings-regular.eot
users/static/users/fonts/glyphicons-halflings-regular.svg
