Metadata-Version: 1.1
Name: hexomega
Version: 0.3
Summary: A package to streamline creation of projects and tasks for Murdoch University.
Home-page: https://www.github.com/defstryker/Hex-Omega
Author: Abhi Rudra
Author-email: defstryker@hotmail.com
License: MIT License
Platform: UNKNOWN
Classifier: Environment :: Web Environment
Classifier: Framework :: Django
Classifier: Framework :: Django :: 1.10
Classifier: Intended Audience :: Developers
Classifier: License :: OSI Approved :: MIT License
Classifier: Programming Language :: Python
Classifier: Programming Language :: Python :: 3
Classifier: Programming Language :: Python :: 3.4
Classifier: Programming Language :: Python :: 3.5
Classifier: Topic :: Internet :: WWW/HTTP
Classifier: Topic :: Internet :: WWW/HTTP :: Dynamic Content
